segnn_jax/__init__.py
segnn_jax/blocks.py
segnn_jax/config.py
segnn_jax/graph_utils.py
segnn_jax/irreps_computer.py
segnn_jax/segnn.py
segnn_jax-0.7.dist-info/LICENSE
segnn_jax-0.7.dist-info/METADATA
segnn_jax-0.7.dist-info/WHEEL
segnn_jax-0.7.dist-info/top_level.txt
segnn_jax-0.7.dist-info/RECORD
